pybuilder_pytest_too/__init__.py
pybuilder_pytest_too/version.py
pybuilder_pytest_too-17.dist-info/METADATA
pybuilder_pytest_too-17.dist-info/WHEEL
pybuilder_pytest_too-17.dist-info/namespace_packages.txt
pybuilder_pytest_too-17.dist-info/top_level.txt
pybuilder_pytest_too-17.dist-info/zip-safe
pybuilder_pytest_too-17.dist-info/RECORD
