Metadata-Version: 2.1
Name: pybuilder-pytest-too
Version: 17
Summary: PyBuilder Pytest Plugin
Home-page: https://github.com/AlexeySanko/pybuilder_pytest
Author: Alexey Sanko
Author-email: alexeycount@gmail.com
Maintainer: 
Maintainer-email: 
License: Apache License, Version 2.0
Classifier: Development Status :: 4 - Beta
Classifier: Environment :: Console
Classifier: Intended Audience :: Developers
Classifier: License :: OSI Approved :: Apache Software License
Classifier: Programming Language :: Python
Classifier: Programming Language :: Python :: 2
Classifier: Programming Language :: Python :: 2.7
Classifier: Programming Language :: Python :: 3
Classifier: Programming Language :: Python :: 3.2
Classifier: Programming Language :: Python :: 3.3
Classifier: Programming Language :: Python :: 3.4
Classifier: Programming Language :: Python :: 3.5
Classifier: Programming Language :: Python :: 3.6
Requires-Dist: pytest
